<?xml version="1.0" encoding="utf-8"?>
<abapGit version="v1.0.0" serializer="LCL_OBJECT_WAPA" serializer_version="v1.0.0">
 <asx:abap xmlns:asx="http://www.sap.com/abapxml" version="1.0">
  <asx:values>
   <ATTRIBUTES>
    <APPLNAME>ZCOMPLOADER_LIB</APPLNAME>
    <APPLCLAS>/UI5/CL_UI5_BSP_APPLICATION</APPLCLAS>
    <APPLEXT>ZCOMPLOADER_LIB</APPLEXT>
    <SECURITY>X</SECURITY>
    <ORIGLANG>E</ORIGLANG>
    <MODIFLANG>E</MODIFLANG>
    <TEXT>Component Loader Lib</TEXT>
   </ATTRIBUTES>
   <PAGES>
    <item>
     <ATTRIBUTES>
      <APPLNAME>ZCOMPLOADER_LIB</APPLNAME>
      <PAGEKEY>.LIBRARY</PAGEKEY>
      <PAGENAME>.library</PAGENAME>
      <PAGETYPE>X</PAGETYPE>
      <LAYOUTLANGU>E</LAYOUTLANGU>
      <VERSION>A</VERSION>
      <LANGU>E</LANGU>
     </ATTRIBUTES>
    </item>
    <item>
     <ATTRIBUTES>
      <APPLNAME>ZCOMPLOADER_LIB</APPLNAME>
      <PAGEKEY>CL/BASECONTROLLER.JS</PAGEKEY>
      <PAGENAME>cl/BaseController.js</PAGENAME>
      <PAGETYPE>X</PAGETYPE>
      <LAYOUTLANGU>E</LAYOUTLANGU>
      <VERSION>A</VERSION>
      <LANGU>E</LANGU>
     </ATTRIBUTES>
    </item>
    <item>
     <ATTRIBUTES>
      <APPLNAME>ZCOMPLOADER_LIB</APPLNAME>
      <PAGEKEY>CL/RESOURCES.JSON</PAGEKEY>
      <PAGENAME>cl/resources.json</PAGENAME>
      <PAGETYPE>X</PAGETYPE>
      <LAYOUTLANGU>E</LAYOUTLANGU>
      <VERSION>A</VERSION>
      <LANGU>E</LANGU>
     </ATTRIBUTES>
    </item>
    <item>
     <ATTRIBUTES>
      <APPLNAME>ZCOMPLOADER_LIB</APPLNAME>
      <PAGEKEY>CL/UICOMPONENT.JS</PAGEKEY>
      <PAGENAME>cl/UIComponent.js</PAGENAME>
      <PAGETYPE>X</PAGETYPE>
      <LAYOUTLANGU>E</LAYOUTLANGU>
      <VERSION>A</VERSION>
      <LANGU>E</LANGU>
     </ATTRIBUTES>
    </item>
    <item>
     <ATTRIBUTES>
      <APPLNAME>ZCOMPLOADER_LIB</APPLNAME>
      <PAGEKEY>CONTROLLERS/BASECONTROLLER.JS</PAGEKEY>
      <PAGENAME>controllers/BaseController.js</PAGENAME>
      <PAGETYPE>X</PAGETYPE>
      <LAYOUTLANGU>E</LAYOUTLANGU>
      <VERSION>A</VERSION>
      <LANGU>E</LANGU>
     </ATTRIBUTES>
    </item>
    <item>
     <ATTRIBUTES>
      <APPLNAME>ZCOMPLOADER_LIB</APPLNAME>
      <PAGEKEY>CONTROLLERS/ERRORHANDLER.JS</PAGEKEY>
      <PAGENAME>controllers/ErrorHandler.js</PAGENAME>
      <PAGETYPE>X</PAGETYPE>
      <LAYOUTLANGU>E</LAYOUTLANGU>
      <VERSION>A</VERSION>
      <LANGU>E</LANGU>
     </ATTRIBUTES>
    </item>
    <item>
     <ATTRIBUTES>
      <APPLNAME>ZCOMPLOADER_LIB</APPLNAME>
      <PAGEKEY>LIBRARY.JS</PAGEKEY>
      <PAGENAME>library.js</PAGENAME>
      <PAGETYPE>X</PAGETYPE>
      <LAYOUTLANGU>E</LAYOUTLANGU>
      <VERSION>A</VERSION>
      <LANGU>E</LANGU>
     </ATTRIBUTES>
    </item>
    <item>
     <ATTRIBUTES>
      <APPLNAME>ZCOMPLOADER_LIB</APPLNAME>
      <PAGEKEY>MANIFEST.JSON</PAGEKEY>
      <PAGENAME>manifest.json</PAGENAME>
      <PAGETYPE>X</PAGETYPE>
      <LAYOUTLANGU>E</LAYOUTLANGU>
      <VERSION>A</VERSION>
      <LANGU>E</LANGU>
     </ATTRIBUTES>
    </item>
    <item>
     <ATTRIBUTES>
      <APPLNAME>ZCOMPLOADER_LIB</APPLNAME>
      <PAGEKEY>MESSAGEBUNDLE.PROPERTIES</PAGEKEY>
      <PAGENAME>messagebundle.properties</PAGENAME>
      <PAGETYPE>X</PAGETYPE>
      <LAYOUTLANGU>E</LAYOUTLANGU>
      <VERSION>A</VERSION>
      <LANGU>E</LANGU>
     </ATTRIBUTES>
    </item>
    <item>
     <ATTRIBUTES>
      <APPLNAME>ZCOMPLOADER_LIB</APPLNAME>
      <PAGEKEY>OBJECTS/BASEOBJECT.JS</PAGEKEY>
      <PAGENAME>objects/BaseObject.js</PAGENAME>
      <PAGETYPE>X</PAGETYPE>
      <LAYOUTLANGU>E</LAYOUTLANGU>
      <VERSION>A</VERSION>
      <LANGU>E</LANGU>
     </ATTRIBUTES>
    </item>
    <item>
     <ATTRIBUTES>
      <APPLNAME>ZCOMPLOADER_LIB</APPLNAME>
      <PAGEKEY>OBJECTS/BASESERVICE.JS</PAGEKEY>
      <PAGENAME>objects/BaseService.js</PAGENAME>
      <PAGETYPE>X</PAGETYPE>
      <LAYOUTLANGU>E</LAYOUTLANGU>
      <VERSION>A</VERSION>
      <LANGU>E</LANGU>
     </ATTRIBUTES>
    </item>
    <item>
     <ATTRIBUTES>
      <APPLNAME>ZCOMPLOADER_LIB</APPLNAME>
      <PAGEKEY>OBJECTS/BASESTATE.JS</PAGEKEY>
      <PAGENAME>objects/BaseState.js</PAGENAME>
      <PAGETYPE>X</PAGETYPE>
      <LAYOUTLANGU>E</LAYOUTLANGU>
      <VERSION>A</VERSION>
      <LANGU>E</LANGU>
     </ATTRIBUTES>
    </item>
    <item>
     <ATTRIBUTES>
      <APPLNAME>ZCOMPLOADER_LIB</APPLNAME>
      <PAGEKEY>RESOURCES.JSON</PAGEKEY>
      <PAGENAME>resources.json</PAGENAME>
      <PAGETYPE>X</PAGETYPE>
      <LAYOUTLANGU>E</LAYOUTLANGU>
      <VERSION>A</VERSION>
      <LANGU>E</LANGU>
     </ATTRIBUTES>
    </item>
    <item>
     <ATTRIBUTES>
      <APPLNAME>ZCOMPLOADER_LIB</APPLNAME>
      <PAGEKEY>TYPES/CENTRALENTRYPOINTTYPE.JS</PAGEKEY>
      <PAGENAME>types/CentralEntryPointType.js</PAGENAME>
      <PAGETYPE>X</PAGETYPE>
      <LAYOUTLANGU>E</LAYOUTLANGU>
      <VERSION>A</VERSION>
      <LANGU>E</LANGU>
     </ATTRIBUTES>
    </item>
    <item>
     <ATTRIBUTES>
      <APPLNAME>ZCOMPLOADER_LIB</APPLNAME>
      <PAGEKEY>UI5207FD1EFD24ED15530219A54886531DA7EBBB23D</PAGEKEY>
      <PAGENAME>UI5207FD1EFD24ED15530219A54886531DA7EBBB23D</PAGENAME>
      <PAGETYPE>X</PAGETYPE>
      <LAYOUTLANGU>E</LAYOUTLANGU>
      <VERSION>A</VERSION>
      <LANGU>E</LANGU>
     </ATTRIBUTES>
    </item>
    <item>
     <ATTRIBUTES>
      <APPLNAME>ZCOMPLOADER_LIB</APPLNAME>
      <PAGEKEY>UI5223FEBE9D010BBB1369E78BD61E2FC6A765A4415</PAGEKEY>
      <PAGENAME>UI5223FEBE9D010BBB1369E78BD61E2FC6A765A4415</PAGENAME>
      <PAGETYPE>X</PAGETYPE>
      <LAYOUTLANGU>E</LAYOUTLANGU>
      <VERSION>A</VERSION>
      <LANGU>E</LANGU>
     </ATTRIBUTES>
    </item>
    <item>
     <ATTRIBUTES>
      <APPLNAME>ZCOMPLOADER_LIB</APPLNAME>
      <PAGEKEY>UI5359BB3E4BBF0D0A93CEE6594359136000D4FBA6E</PAGEKEY>
      <PAGENAME>UI5359BB3E4BBF0D0A93CEE6594359136000D4FBA6E</PAGENAME>
      <PAGETYPE>X</PAGETYPE>
      <LAYOUTLANGU>E</LAYOUTLANGU>
      <VERSION>A</VERSION>
      <LANGU>E</LANGU>
     </ATTRIBUTES>
    </item>
    <item>
     <ATTRIBUTES>
      <APPLNAME>ZCOMPLOADER_LIB</APPLNAME>
      <PAGEKEY>UI54A3FE66A66ADFF0956A5B0377BC80E53B91B8ED2</PAGEKEY>
      <PAGENAME>UI54A3FE66A66ADFF0956A5B0377BC80E53B91B8ED2</PAGENAME>
      <PAGETYPE>X</PAGETYPE>
      <LAYOUTLANGU>E</LAYOUTLANGU>
      <VERSION>A</VERSION>
      <LANGU>E</LANGU>
     </ATTRIBUTES>
    </item>
    <item>
     <ATTRIBUTES>
      <APPLNAME>ZCOMPLOADER_LIB</APPLNAME>
      <PAGEKEY>UI55225BAF4287AB11742C54EC786D61A9CF9F41150</PAGEKEY>
      <PAGENAME>UI55225BAF4287AB11742C54EC786D61A9CF9F41150</PAGENAME>
      <PAGETYPE>X</PAGETYPE>
      <LAYOUTLANGU>E</LAYOUTLANGU>
      <VERSION>A</VERSION>
      <LANGU>E</LANGU>
     </ATTRIBUTES>
    </item>
    <item>
     <ATTRIBUTES>
      <APPLNAME>ZCOMPLOADER_LIB</APPLNAME>
      <PAGEKEY>UI56CAA3F98C646FA80C04CC41A7F15F3D87C7494CC</PAGEKEY>
      <PAGENAME>UI56CAA3F98C646FA80C04CC41A7F15F3D87C7494CC</PAGENAME>
      <PAGETYPE>X</PAGETYPE>
      <LAYOUTLANGU>E</LAYOUTLANGU>
      <VERSION>A</VERSION>
      <LANGU>E</LANGU>
     </ATTRIBUTES>
    </item>
    <item>
     <ATTRIBUTES>
      <APPLNAME>ZCOMPLOADER_LIB</APPLNAME>
      <PAGEKEY>UI59A58CB7DCEF624336C59D226B8E687EAC2AD44AD</PAGEKEY>
      <PAGENAME>UI59A58CB7DCEF624336C59D226B8E687EAC2AD44AD</PAGENAME>
      <PAGETYPE>X</PAGETYPE>
      <LAYOUTLANGU>E</LAYOUTLANGU>
      <VERSION>A</VERSION>
      <LANGU>E</LANGU>
     </ATTRIBUTES>
    </item>
    <item>
     <ATTRIBUTES>
      <APPLNAME>ZCOMPLOADER_LIB</APPLNAME>
      <PAGEKEY>UI5CAC39AF281D298E3BE4EFB455CC249FCF04112C2</PAGEKEY>
      <PAGENAME>UI5CAC39AF281D298E3BE4EFB455CC249FCF04112C2</PAGENAME>
      <PAGETYPE>X</PAGETYPE>
      <LAYOUTLANGU>E</LAYOUTLANGU>
      <VERSION>A</VERSION>
      <LANGU>E</LANGU>
     </ATTRIBUTES>
    </item>
    <item>
     <ATTRIBUTES>
      <APPLNAME>ZCOMPLOADER_LIB</APPLNAME>
      <PAGEKEY>UI5CF445F595418C7B7402A7652260E6F71CA274399</PAGEKEY>
      <PAGENAME>UI5CF445F595418C7B7402A7652260E6F71CA274399</PAGENAME>
      <PAGETYPE>X</PAGETYPE>
      <LAYOUTLANGU>E</LAYOUTLANGU>
      <VERSION>A</VERSION>
      <LANGU>E</LANGU>
     </ATTRIBUTES>
    </item>
    <item>
     <ATTRIBUTES>
      <APPLNAME>ZCOMPLOADER_LIB</APPLNAME>
      <PAGEKEY>UI5DDBA7AF97F48EB7D4973B51E3CB5B79E8590DB6B</PAGEKEY>
      <PAGENAME>UI5DDBA7AF97F48EB7D4973B51E3CB5B79E8590DB6B</PAGENAME>
      <PAGETYPE>X</PAGETYPE>
      <LAYOUTLANGU>E</LAYOUTLANGU>
      <VERSION>A</VERSION>
      <LANGU>E</LANGU>
     </ATTRIBUTES>
    </item>
    <item>
     <ATTRIBUTES>
      <APPLNAME>ZCOMPLOADER_LIB</APPLNAME>
      <PAGEKEY>UI5REPOSITORYPATHMAPPING.XML</PAGEKEY>
      <PAGENAME>UI5RepositoryPathMapping.xml</PAGENAME>
      <PAGETYPE>X</PAGETYPE>
      <LAYOUTLANGU>E</LAYOUTLANGU>
      <VERSION>A</VERSION>
      <LANGU>E</LANGU>
     </ATTRIBUTES>
    </item>
   </PAGES>
  </asx:values>
 </asx:abap>
</abapGit>
